{"singlePage": [], "startSite": "", "filingNum": "", "onePageListNum": 15, "commentLabelColor": "#006b75", "yearColorList": ["#bc4c00", "#0969da", "#1f883d", "#A333D0"], "i18n": "CN", "themeMode": "manual", "dayTheme": "light", "nightTheme": "dark", "urlMode": "pinyin", "script": "", "style": "", "indexScript": "", "indexStyle": "", "bottomText": "", "showPostSource": 1, "iconList": {}, "UTC": 8, "rssSplit": "sentence", "exlink": {}, "title": "Blog Title", "subTitle": "Blog description", "avatarUrl": "https://github.githubassets.com/favicons/favicon.svg", "GMEEK_VERSION": "last", "postListJson": {"P1": {"htmlDir": "docs/post/BingAI--lai-zi-Microsoft-de-liao-tian-ji-qi-ren.html", "labels": ["help wanted"], "postTitle": "BingAI-\u6765\u81eaMicrosoft\u7684\u804a\u5929\u673a\u5668\u4eba", "postUrl": "post/BingAI--lai-zi-Microsoft-de-liao-tian-ji-qi-ren.html", "postSourceUrl": "https://github.com/zpc2024c/zpc2024c.github.io/issues/1", "commentNum": 0, "wordCount": 52, "description": "\u4f5c\u8005\u81ea\u5df1\u642d\u5efa\u7684\u7f51\u7ad9\u3010\u514d\u8d39\u3011\r\n[https://bingai.zpc.cloudns.be/web/0]\u3002", "top": 0, "createdAt": 1719058329, "style": "", "script": "", "ogImage": "https://github.githubassets.com/favicons/favicon.svg", "createdDate": "2024-06-22", "dateLabelColor": "#bc4c00"}}, "singeListJson": {}, "labelColorDict": {"bug": "#d73a4a", "documentation": "#0075ca", "duplicate": "#cfd3d7", "enhancement": "#a2eeef", "good first issue": "#7057ff", "help wanted": "#008672", "invalid": "#e4e669", "question": "#d876e3", "wontfix": "#ffffff"}, "displayTitle": "Blog Title", "faviconUrl": "https://github.githubassets.com/favicons/favicon.svg", "ogImage": "https://github.githubassets.com/favicons/favicon.svg", "homeUrl": "https://zpc2024c.github.io", "prevUrl": "disabled", "nextUrl": "disabled"}